{"__type__":"cc.JsonAsset","_name":"part_subject_tag_db","json":{"types":["I","S","I","I","I","I","I","I"],"fields":["id","text","R","G","B","borderR","borderG","borderB"],"values":[["1","简约","82","155","255","255","255","255"],["2","华丽","216","81","255","255","255","255"],["3","成熟","133","78","78","255","255","255"],["4","天真","106","193","59","255","255","255"],["5","清凉","51","177","164","255","255","255"],["6","保暖","235","122","53","255","255","255"],["7","日常","102","129","205","255","255","255"],["8","幻想","255","91","222","255","255","255"],["9","文静","62","189","255","255","255","255"],["10","运动","108","111","239","255","255","255"],["11","淡雅","51","174","97","255","255","255"],["12","鲜艳","255","0","90","255","255","255"],["13","冷色","55","107","213","255","255","255"],["14","暖色","255","90","129","255","255","255"],["15","古风","142","97","255","255","255","255"],["16","现代","89","89","89","255","255","255"],["17","欧式","119","93","234","255","255","255"],["18","童话","255","88","182","255","255","255"],["19","民俗","216","138","15","255","255","255"],["20","魔法","144","36","255","255","255","255"]]}}